<?xml version="1.0" encoding="utf-8" ?>
<dwsync>
<file name="Controller.php" server="93.90.186.204//markusmorley.de/octoberbasic/" local="131999102758204606" remote="131999115600000000" Dst="2" />
<file name="Content.php" server="93.90.186.204//markusmorley.de/octoberbasic/" local="131999102758204606" remote="131999115600000000" Dst="2" />
<file name="Menu.php" server="93.90.186.204//markusmorley.de/octoberbasic/" local="131999102758214598" remote="131999115600000000" Dst="2" />
<file name="MenuItemReference.php" server="93.90.186.204//markusmorley.de/octoberbasic/" local="131999102758244572" remote="131999115600000000" Dst="2" />
<file name="MenuItem.php" server="93.90.186.204//markusmorley.de/octoberbasic/" local="131999102758224589" remote="131999115600000000" Dst="2" />
<file name="Page.php" server="93.90.186.204//markusmorley.de/octoberbasic/" local="131999102758254564" remote="131999115600000000" Dst="2" />
<file name="PageList.php" server="93.90.186.204//markusmorley.de/octoberbasic/" local="131999102758264556" remote="131999115600000000" Dst="2" />
<file name="Router.php" server="93.90.186.204//markusmorley.de/octoberbasic/" local="131999102758274566" remote="131999115600000000" Dst="2" />
<file name="Snippet.php" server="93.90.186.204//markusmorley.de/octoberbasic/" local="131999102758284553" remote="131999115600000000" Dst="2" />
<file name="SnippetManager.php" server="93.90.186.204//markusmorley.de/octoberbasic/" local="131999102758294534" remote="131999115600000000" Dst="2" />
</dwsync>