<?xml version="1.0" encoding="utf-8" ?>
<dwsync>
<file name="IndexControllerOperations.php" server="93.90.186.204//markusmorley.de/octoberbasic/" local="131996631041169983" remote="131996631000000000" Dst="2" />
<file name="IndexDataRegistry.php" server="93.90.186.204//markusmorley.de/octoberbasic/" local="131996631041179975" remote="131996631000000000" Dst="2" />
<file name="IndexDatabaseTableOperations.php" server="93.90.186.204//markusmorley.de/octoberbasic/" local="131996631041189967" remote="131996631000000000" Dst="2" />
<file name="IndexLocalizationOperations.php" server="93.90.186.204//markusmorley.de/octoberbasic/" local="131996631041199963" remote="131996631000000000" Dst="2" />
<file name="IndexMenusOperations.php" server="93.90.186.204//markusmorley.de/octoberbasic/" local="131996631041209954" remote="131996631000000000" Dst="2" />
<file name="IndexModelFormOperations.php" server="93.90.186.204//markusmorley.de/octoberbasic/" local="131996631041209954" remote="131996631000000000" Dst="2" />
<file name="IndexModelListOperations.php" server="93.90.186.204//markusmorley.de/octoberbasic/" local="131996631041219945" remote="131996631000000000" Dst="2" />
<file name="IndexModelOperations.php" server="93.90.186.204//markusmorley.de/octoberbasic/" local="131996631041229938" remote="131996631000000000" Dst="2" />
<file name="IndexPermissionsOperations.php" server="93.90.186.204//markusmorley.de/octoberbasic/" local="131996631041239928" remote="131996631000000000" Dst="2" />
<file name="IndexPluginOperations.php" server="93.90.186.204//markusmorley.de/octoberbasic/" local="131996631041249921" remote="131996631000000000" Dst="2" />
<file name="IndexVersionsOperations.php" server="93.90.186.204//markusmorley.de/octoberbasic/" local="131996631041259913" remote="131996631000000000" Dst="2" />
</dwsync>